mms/__init__.py
mms/arg_parser.py
mms/context.py
mms/export_model.py
mms/model_loader.py
mms/model_server.py
mms/model_service_worker.py
mms/service.py
mms/version.py
mms/configs/sagemaker_config.properties
mms/frontend/model-server.jar
mms/metrics/__init__.py
mms/metrics/dimension.py
mms/metrics/metric.py
mms/metrics/metric_collector.py
mms/metrics/metric_encoder.py
mms/metrics/metrics_store.py
mms/metrics/process_memory_metric.py
mms/metrics/system_metrics.py
mms/metrics/unit.py
mms/model_service/__init__.py
mms/model_service/gluon_vision_service.py
mms/model_service/model_service.py
mms/model_service/mxnet_model_service.py
mms/model_service/mxnet_vision_service.py
mms/protocol/__init__.py
mms/protocol/otf_message_handler.py
mms/utils/__init__.py
mms/utils/timeit_decorator.py
mms/utils/mxnet/__init__.py
mms/utils/mxnet/image.py
mms/utils/mxnet/ndarray.py
mms/utils/mxnet/nlp.py
mxnet_model_server_prometheus-1.0.8b20190923.dist-info/LICENSE
mxnet_model_server_prometheus-1.0.8b20190923.dist-info/LICENSE.txt
mxnet_model_server_prometheus-1.0.8b20190923.dist-info/METADATA
mxnet_model_server_prometheus-1.0.8b20190923.dist-info/WHEEL
mxnet_model_server_prometheus-1.0.8b20190923.dist-info/entry_points.txt
mxnet_model_server_prometheus-1.0.8b20190923.dist-info/top_level.txt
mxnet_model_server_prometheus-1.0.8b20190923.dist-info/RECORD
